PegParser
