Metadata-Version: 2.2
Name: PegParser
Version: 0.0.2
Summary: This package implements a PEG (Parsing Expression Grammar) to parse syntax, i add rules to parse URL, HTTP request and response easily with security and some format like hexadecimal, base32, base64, base85...
Home-page: https://github.com/mauricelambert/PegParser
Author: Maurice Lambert
Author-email: Maurice Lambert <mauricelambert434@gmail.com>
Maintainer: Maurice Lambert
Maintainer-email: Maurice Lambert <mauricelambert434@gmail.com>
License: GPL-3.0 License
Project-URL: Github, https://github.com/mauricelambert/PegParser
Project-URL: Documentation, https://mauricelambert.github.io/info/python/security/PegParser.html
Keywords: PEG,URL,HTTP,Parser,base64,hexadecimal,base32,base85
Platform: Windows
Platform: Linux
Platform: MacOS
Classifier: Natural Language :: English
Classifier: Topic :: System :: Networking
Classifier: Topic :: Internet :: WWW/HTTP
Classifier: Programming Language :: Python
Classifier: Intended Audience :: Developers
Classifier: Operating System :: MacOS :: MacOS X
Classifier: Programming Language :: Python :: 3.8
Classifier: Operating System :: Microsoft :: Windows
Classifier: Development Status :: 5 - Production/Stable
Classifier: License :: OSI Approved :: GNU General Public License v3 or later (GPLv3+)
Requires-Python: >=3.8
License-File: LICENSE.txt
Dynamic: author
Dynamic: home-page
Dynamic: maintainer
Dynamic: requires-python
